<?xml version="1.0" encoding="UTF-8"?><record_update sys_domain="global" table="sys_ux_page_property">
    <sys_ux_page_property action="DELETE">
        <choices/>
        <description>Header Configuration</description>
        <name>chrome_header</name>
        <page display_value="BEAUTIFY">c054d21543a231106448024798b65235</page>
        <required_translations>[ {
  "message" : "Configure workspace",
  "comment" : ""
}, {
  "message" : "Display Preferences",
  "comment" : ""
}, {
  "message" : "Notifications",
  "comment" : ""
}, {
  "message" : "Settings",
  "comment" : ""
}, {
  "message" : "Show Badge Count",
  "comment" : ""
}, {
  "message" : "Show Banners",
  "comment" : ""
}, {
  "message" : "Show ribbon",
  "comment" : ""
}, {
  "message" : "Show sidebar",
  "comment" : ""
}, {
  "message" : "UserMenu",
  "comment" : ""
}, {
  "message" : "Wrap list text",
  "comment" : ""
} ]</required_translations>
        <route/>
        <suffix/>
        <sys_class_name>sys_ux_page_property</sys_class_name>
        <sys_created_by>gilpares</sys_created_by>
        <sys_created_on>2023-11-15 22:53:55</sys_created_on>
        <sys_domain>global</sys_domain>
        <sys_domain_path>global</sys_domain_path>
        <sys_id>0054d215f4a231109621dc2972d31b22</sys_id>
        <sys_mod_count>1</sys_mod_count>
        <sys_name>chrome_header</sys_name>
        <sys_package display_value="BEAUTIFY" source="x_1207268_beautify">8d072b249322311054597bfdfaba100b</sys_package>
        <sys_policy/>
        <sys_scope display_value="BEAUTIFY">8d072b249322311054597bfdfaba100b</sys_scope>
        <sys_update_name>sys_ux_page_property_0054d215f4a231109621dc2972d31b22</sys_update_name>
        <sys_updated_by>gilpares</sys_updated_by>
        <sys_updated_on>2023-11-15 22:53:59</sys_updated_on>
        <type>json</type>
        <unique_name>x_1207268_beautify.c054d21543a231106448024798b65235.root.chrome_header</unique_name>
        <value>{&#13;
    "privatePage": {&#13;
        "notificationsEnabled": true,&#13;
        "searchEnabled": true,&#13;
        "userPrefsEnabled": true,&#13;
        "contextualConfigurationItems": {&#13;
            "_roles": [&#13;
                "workspace_admin"&#13;
            ],&#13;
            "enabled": true,&#13;
            "position": 150&#13;
        },&#13;
        "globalTools": {&#13;
            "collapsingMenuId": 0,&#13;
            "primaryItems": [{&#13;
                "label": "UserMenu",&#13;
                "icon": "user",&#13;
                "type": "menu",&#13;
                "primaryDisplay": "icon",&#13;
                "value": {&#13;
                    "children": [{&#13;
                            "_roles": [&#13;
                                "workspace_admin"&#13;
                            ],&#13;
                            "label": {&#13;
                                "message": "Configure workspace",&#13;
                                "translatable": true&#13;
                            },&#13;
                            "type": "navigation",&#13;
                            "position": 100,&#13;
                            "primaryDisplay": "none",&#13;
                            "value": {&#13;
                                "type": "external",&#13;
                                "opensWindow": "true",&#13;
                                "value": {&#13;
                                    "href": "/nav_to.do?uri=/sys_ux_app_config.do?sys_id=1854d2154ba231104fde278e273ed835"&#13;
                                }&#13;
                            }&#13;
                        },&#13;
                        {&#13;
                            "label": {&#13;
                                "message": "Settings",&#13;
                                "translatable": true&#13;
                            },&#13;
                            "type": "menu",&#13;
                            "position": 50,&#13;
                            "value": {&#13;
                                "children": [{&#13;
                                        "label": {&#13;
                                            "message": "Display Preferences",&#13;
                                            "translatable": true&#13;
                                        },&#13;
                                        "type": "divider"&#13;
                                    },&#13;
                                    {&#13;
                                        "label": {&#13;
                                            "message": "Show ribbon",&#13;
                                            "translatable": true&#13;
                                        },&#13;
                                        "type": "toggle",&#13;
                                        "value": {&#13;
                                            "_meta": {&#13;
                                                "_type": "userPreferences",&#13;
                                                "_path": "userPrefName",&#13;
                                                "_value": {&#13;
                                                    "userPrefName": "workspace.showRibbon"&#13;
                                                },&#13;
                                                "_default": {&#13;
                                                    "userPrefName": "true"&#13;
                                                }&#13;
                                            }&#13;
                                        }&#13;
                                    },&#13;
                                    {&#13;
                                        "label": {&#13;
                                            "message": "Show sidebar",&#13;
                                            "translatable": true&#13;
                                        },&#13;
                                        "type": "toggle",&#13;
                                        "value": {&#13;
                                            "_meta": {&#13;
                                                "_type": "userPreferences",&#13;
                                                "_path": "userPrefName",&#13;
                                                "_value": {&#13;
                                                    "userPrefName": "workspace.showAgentAssist"&#13;
                                                },&#13;
                                                "_default": {&#13;
                                                    "userPrefName": "true"&#13;
                                                }&#13;
                                            }&#13;
                                        }&#13;
                                    },&#13;
                                    {&#13;
                                        "label": {&#13;
                                            "message": "Wrap list text",&#13;
                                            "translatable": true&#13;
                                        },&#13;
                                        "type": "toggle",&#13;
                                        "value": {&#13;
                                            "_meta": {&#13;
                                                "_type": "userPreferences",&#13;
                                                "_path": "userPrefName",&#13;
                                                "_value": {&#13;
                                                    "userPrefName": "workspace.wrapListText"&#13;
                                                },&#13;
                                                "_default": {&#13;
                                                    "userPrefName": "true"&#13;
                                                }&#13;
                                            }&#13;
                                        }&#13;
                                    },&#13;
                                    {&#13;
                                        "label": {&#13;
                                            "message": "Notifications",&#13;
                                            "translatable": true&#13;
                                        },&#13;
                                        "type": "divider"&#13;
                                    },&#13;
                                    {&#13;
                                        "label": {&#13;
                                            "message": "Show Banners",&#13;
                                            "translatable": true&#13;
                                        },&#13;
                                        "type": "toggle",&#13;
                                        "value": {&#13;
                                            "_meta": {&#13;
                                                "_type": "userPreferences",&#13;
                                                "_path": "userPrefName",&#13;
                                                "_value": {&#13;
                                                    "userPrefName": "workspace.notifications.showPopups"&#13;
                                                },&#13;
                                                "_default": {&#13;
                                                    "userPrefName": "true"&#13;
                                                }&#13;
                                            }&#13;
                                        }&#13;
                                    },&#13;
                                    {&#13;
                                        "label": {&#13;
                                            "message": "Show Badge Count",&#13;
                                            "translatable": true&#13;
                                        },&#13;
                                        "type": "toggle",&#13;
                                        "value": {&#13;
                                            "_meta": {&#13;
                                                "_type": "userPreferences",&#13;
                                                "_path": "userPrefName",&#13;
                                                "_value": {&#13;
                                                    "userPrefName": "workspace.notifications.showBadgeCount"&#13;
                                                },&#13;
                                                "_default": {&#13;
                                                    "userPrefName": "true"&#13;
                                                }&#13;
                                            }&#13;
                                        }&#13;
                                    }&#13;
                                ]&#13;
                            }&#13;
                        }&#13;
                    ]&#13;
                }&#13;
            }],&#13;
            "secondaryItems": [&#13;
&#13;
            ]&#13;
        }&#13;
    },&#13;
    "publicPage": {&#13;
        "actionButtons": [&#13;
&#13;
        ]&#13;
    }&#13;
}</value>
    </sys_ux_page_property>
    <sys_translated_text action="DELETE" query="documentkey=0054d215f4a231109621dc2972d31b22"/>
    <sys_update_version action="INSERT_OR_UPDATE">
        <action>DELETE</action>
        <application display_value="BEAUTIFY">8d072b249322311054597bfdfaba100b</application>
        <file_path/>
        <instance_id>0d96f4badbc63950f697684e139619a3</instance_id>
        <instance_name>dev194372</instance_name>
        <name>sys_ux_page_property_0054d215f4a231109621dc2972d31b22</name>
        <payload><![CDATA[<?xml version="1.0" encoding="UTF-8"?><record_update sys_domain="global" table="sys_ux_page_property"><sys_ux_page_property action="INSERT_OR_UPDATE"><choices/><description>Header Configuration</description><name>chrome_header</name><page display_value="BEAUTIFY">c054d21543a231106448024798b65235</page><required_translations>[ {
  "message" : "Configure workspace",
  "comment" : ""
}, {
  "message" : "Display Preferences",
  "comment" : ""
}, {
  "message" : "Notifications",
  "comment" : ""
}, {
  "message" : "Settings",
  "comment" : ""
}, {
  "message" : "Show Badge Count",
  "comment" : ""
}, {
  "message" : "Show Banners",
  "comment" : ""
}, {
  "message" : "Show ribbon",
  "comment" : ""
}, {
  "message" : "Show sidebar",
  "comment" : ""
}, {
  "message" : "UserMenu",
  "comment" : ""
}, {
  "message" : "Wrap list text",
  "comment" : ""
} ]</required_translations><route/><suffix/><sys_class_name>sys_ux_page_property</sys_class_name><sys_created_by>gilpares</sys_created_by><sys_created_on>2023-11-15 22:53:55</sys_created_on><sys_domain>global</sys_domain><sys_domain_path>global</sys_domain_path><sys_id>0054d215f4a231109621dc2972d31b22</sys_id><sys_mod_count>1</sys_mod_count><sys_name>chrome_header</sys_name><sys_package display_value="BEAUTIFY" source="x_1207268_beautify">8d072b249322311054597bfdfaba100b</sys_package><sys_policy/><sys_scope display_value="BEAUTIFY">8d072b249322311054597bfdfaba100b</sys_scope><sys_update_name>sys_ux_page_property_0054d215f4a231109621dc2972d31b22</sys_update_name><sys_updated_by>gilpares</sys_updated_by><sys_updated_on>2023-11-15 22:53:59</sys_updated_on><type>json</type><unique_name>x_1207268_beautify.c054d21543a231106448024798b65235.root.chrome_header</unique_name><value>{&#13;
    "privatePage": {&#13;
        "notificationsEnabled": true,&#13;
        "searchEnabled": true,&#13;
        "userPrefsEnabled": true,&#13;
        "contextualConfigurationItems": {&#13;
            "_roles": [&#13;
                "workspace_admin"&#13;
            ],&#13;
            "enabled": true,&#13;
            "position": 150&#13;
        },&#13;
        "globalTools": {&#13;
            "collapsingMenuId": 0,&#13;
            "primaryItems": [{&#13;
                "label": "UserMenu",&#13;
                "icon": "user",&#13;
                "type": "menu",&#13;
                "primaryDisplay": "icon",&#13;
                "value": {&#13;
                    "children": [{&#13;
                            "_roles": [&#13;
                                "workspace_admin"&#13;
                            ],&#13;
                            "label": {&#13;
                                "message": "Configure workspace",&#13;
                                "translatable": true&#13;
                            },&#13;
                            "type": "navigation",&#13;
                            "position": 100,&#13;
                            "primaryDisplay": "none",&#13;
                            "value": {&#13;
                                "type": "external",&#13;
                                "opensWindow": "true",&#13;
                                "value": {&#13;
                                    "href": "/nav_to.do?uri=/sys_ux_app_config.do?sys_id=1854d2154ba231104fde278e273ed835"&#13;
                                }&#13;
                            }&#13;
                        },&#13;
                        {&#13;
                            "label": {&#13;
                                "message": "Settings",&#13;
                                "translatable": true&#13;
                            },&#13;
                            "type": "menu",&#13;
                            "position": 50,&#13;
                            "value": {&#13;
                                "children": [{&#13;
                                        "label": {&#13;
                                            "message": "Display Preferences",&#13;
                                            "translatable": true&#13;
                                        },&#13;
                                        "type": "divider"&#13;
                                    },&#13;
                                    {&#13;
                                        "label": {&#13;
                                            "message": "Show ribbon",&#13;
                                            "translatable": true&#13;
                                        },&#13;
                                        "type": "toggle",&#13;
                                        "value": {&#13;
                                            "_meta": {&#13;
                                                "_type": "userPreferences",&#13;
                                                "_path": "userPrefName",&#13;
                                                "_value": {&#13;
                                                    "userPrefName": "workspace.showRibbon"&#13;
                                                },&#13;
                                                "_default": {&#13;
                                                    "userPrefName": "true"&#13;
                                                }&#13;
                                            }&#13;
                                        }&#13;
                                    },&#13;
                                    {&#13;
                                        "label": {&#13;
                                            "message": "Show sidebar",&#13;
                                            "translatable": true&#13;
                                        },&#13;
                                        "type": "toggle",&#13;
                                        "value": {&#13;
                                            "_meta": {&#13;
                                                "_type": "userPreferences",&#13;
                                                "_path": "userPrefName",&#13;
                                                "_value": {&#13;
                                                    "userPrefName": "workspace.showAgentAssist"&#13;
                                                },&#13;
                                                "_default": {&#13;
                                                    "userPrefName": "true"&#13;
                                                }&#13;
                                            }&#13;
                                        }&#13;
                                    },&#13;
                                    {&#13;
                                        "label": {&#13;
                                            "message": "Wrap list text",&#13;
                                            "translatable": true&#13;
                                        },&#13;
                                        "type": "toggle",&#13;
                                        "value": {&#13;
                                            "_meta": {&#13;
                                                "_type": "userPreferences",&#13;
                                                "_path": "userPrefName",&#13;
                                                "_value": {&#13;
                                                    "userPrefName": "workspace.wrapListText"&#13;
                                                },&#13;
                                                "_default": {&#13;
                                                    "userPrefName": "true"&#13;
                                                }&#13;
                                            }&#13;
                                        }&#13;
                                    },&#13;
                                    {&#13;
                                        "label": {&#13;
                                            "message": "Notifications",&#13;
                                            "translatable": true&#13;
                                        },&#13;
                                        "type": "divider"&#13;
                                    },&#13;
                                    {&#13;
                                        "label": {&#13;
                                            "message": "Show Banners",&#13;
                                            "translatable": true&#13;
                                        },&#13;
                                        "type": "toggle",&#13;
                                        "value": {&#13;
                                            "_meta": {&#13;
                                                "_type": "userPreferences",&#13;
                                                "_path": "userPrefName",&#13;
                                                "_value": {&#13;
                                                    "userPrefName": "workspace.notifications.showPopups"&#13;
                                                },&#13;
                                                "_default": {&#13;
                                                    "userPrefName": "true"&#13;
                                                }&#13;
                                            }&#13;
                                        }&#13;
                                    },&#13;
                                    {&#13;
                                        "label": {&#13;
                                            "message": "Show Badge Count",&#13;
                                            "translatable": true&#13;
                                        },&#13;
                                        "type": "toggle",&#13;
                                        "value": {&#13;
                                            "_meta": {&#13;
                                                "_type": "userPreferences",&#13;
                                                "_path": "userPrefName",&#13;
                                                "_value": {&#13;
                                                    "userPrefName": "workspace.notifications.showBadgeCount"&#13;
                                                },&#13;
                                                "_default": {&#13;
                                                    "userPrefName": "true"&#13;
                                                }&#13;
                                            }&#13;
                                        }&#13;
                                    }&#13;
                                ]&#13;
                            }&#13;
                        }&#13;
                    ]&#13;
                }&#13;
            }],&#13;
            "secondaryItems": [&#13;
&#13;
            ]&#13;
        }&#13;
    },&#13;
    "publicPage": {&#13;
        "actionButtons": [&#13;
&#13;
        ]&#13;
    }&#13;
}</value></sys_ux_page_property><sys_translated_text action="delete_multiple" query="documentkey=0054d215f4a231109621dc2972d31b22"/></record_update>]]></payload>
        <payload_hash>-1317449874</payload_hash>
        <record_name>chrome_header</record_name>
        <reverted_from/>
        <source>16c7f36493a23110d2eff24efaba103f</source>
        <source_table>sys_update_set</source_table>
        <state>previous</state>
        <sys_created_by>gilpares</sys_created_by>
        <sys_created_on>2023-11-15 22:53:59</sys_created_on>
        <sys_id>9154161593a23110d2eff24efaba1072</sys_id>
        <sys_mod_count>0</sys_mod_count>
        <sys_recorded_at>18bd530fc890000001</sys_recorded_at>
        <sys_updated_by>gilpares</sys_updated_by>
        <sys_updated_on>2023-11-15 22:53:59</sys_updated_on>
        <type>UX Page Property</type>
        <update_guid>99541615f6a23110c9476fd9cab84071</update_guid>
        <update_guid_history>99541615f6a23110c9476fd9cab84071:-1317449874,55541615ffa231107a9045cb51c91f70:-1841464649</update_guid_history>
    </sys_update_version>
    <sys_metadata_delete action="INSERT_OR_UPDATE">
        <sys_audit_delete/>
        <sys_class_name>sys_metadata_delete</sys_class_name>
        <sys_created_by>admin</sys_created_by>
        <sys_created_on>2024-01-25 20:28:36</sys_created_on>
        <sys_db_object display_value="" name="sys_ux_page_property">sys_ux_page_property</sys_db_object>
        <sys_id>2f322cf9d3cc4160874f3d358020c900</sys_id>
        <sys_metadata>0054d215f4a231109621dc2972d31b22</sys_metadata>
        <sys_mod_count>0</sys_mod_count>
        <sys_name>chrome_header</sys_name>
        <sys_package display_value="BEAUTIFY" source="x_1207268_beautify">8d072b249322311054597bfdfaba100b</sys_package>
        <sys_parent/>
        <sys_policy/>
        <sys_scope display_value="BEAUTIFY">8d072b249322311054597bfdfaba100b</sys_scope>
        <sys_scope_delete display_value="">023a5b9ab19e4e7680107ab801bc4419</sys_scope_delete>
        <sys_update_name>sys_ux_page_property_0054d215f4a231109621dc2972d31b22</sys_update_name>
        <sys_update_version display_value="sys_ux_page_property_0054d215f4a231109621dc2972d31b22">9154161593a23110d2eff24efaba1072</sys_update_version>
        <sys_updated_by>admin</sys_updated_by>
        <sys_updated_on>2024-01-25 20:28:36</sys_updated_on>
    </sys_metadata_delete>
</record_update>
